pypi_files/__init__.py
pypi_files/__main__.py
pypi_files/cli.py
pypi_files/core.py
pypi_files-0.1.5.dist-info/LICENSE
pypi_files-0.1.5.dist-info/METADATA
pypi_files-0.1.5.dist-info/WHEEL
pypi_files-0.1.5.dist-info/entry_points.txt
pypi_files-0.1.5.dist-info/RECORD
