Metadata-Version: 2.1
Name: pypi-files
Version: 0.1.5
Summary: Check and download package source files from PyPI.
Home-page: https://github.com/rcmdnk/pypi-files
License: Apache-2.0
Keywords: PyPI
Author: rcmdnk
Author-email: rcmdnk@gmail.com
Requires-Python: >=3.7,<4.0
Classifier: License :: OSI Approved :: Apache Software License
Classifier: Programming Language :: Python :: 3
Classifier: Programming Language :: Python :: 3.7
Classifier: Programming Language :: Python :: 3.8
Classifier: Programming Language :: Python :: 3.9
Classifier: Programming Language :: Python :: 3.10
Classifier: Programming Language :: Python :: 3.11
Requires-Dist: PyYAML (>=5.4.1,<6.0.0)
Requires-Dist: fire (>=0.4.0,<0.5.0)
Requires-Dist: requests (>=2.26.0,<3.0.0)
Project-URL: Repository, https://github.com/rcmdnk/pypi-files
